flask_once.py
flask_once-0.0.2.dist-info/METADATA
flask_once-0.0.2.dist-info/WHEEL
flask_once-0.0.2.dist-info/top_level.txt
flask_once-0.0.2.dist-info/RECORD
