Metadata-Version: 2.1
Name: flask-once
Version: 0.0.2
Summary: Idempotent Flask Endpoints
Home-page: UNKNOWN
Author: S. Williams-Wynn
Author-email: s.williamswynn.mail@gmail.com
License: UNKNOWN
Platform: UNKNOWN
Requires-Python: >=3.6
Requires-Dist: Flask
Requires-Dist: wrapt
